README.md
setup.cfg
setup.py
ilangbd/__init__.py
ilangbd/func.py
ilangbd/main.py
ilangbd.egg-info/PKG-INFO
ilangbd.egg-info/SOURCES.txt
ilangbd.egg-info/dependency_links.txt
ilangbd.egg-info/entry_points.txt
ilangbd.egg-info/requires.txt
ilangbd.egg-info/top_level.txt
ilangbd.egg-info/zip-safe
test/test.py