Metadata-Version: 1.0
Name: ilangbd
Version: 0.2.1
Summary: A console application of speaking made with Baidu Yuyin
Home-page: https://github.com/yuanzhoucq/ilangbd
Author: joyuer
Author-email: yuanzhou.cq@gmail.com
License: MIT
Platform: UNKNOWN
